dic_analysis/__init__.py
dic_analysis/dic.py
dic_analysis/downloader.py
dic_analysis/io.py
dic_analysis-0.3.1.dist-info/LICENCE
dic_analysis-0.3.1.dist-info/METADATA
dic_analysis-0.3.1.dist-info/WHEEL
dic_analysis-0.3.1.dist-info/top_level.txt
dic_analysis-0.3.1.dist-info/RECORD
