Metadata-Version: 2.1
Name: dic-analysis
Version: 0.3.1
Summary: Functions for analysis of tensile DIC experiments
Home-page: UNKNOWN
Author: Peter Crowther
Author-email: 
License: MIT
Platform: UNKNOWN
Classifier: Programming Language :: Python :: 3
Classifier: License :: OSI Approved :: GNU General Public License v3 (GPLv3)
Classifier: Operating System :: OS Independent
Classifier: License :: OSI Approved :: MIT License
Classifier: Development Status :: 3 - Alpha
Requires-Dist: pandas
Requires-Dist: numpy
Requires-Dist: tqdm
Requires-Dist: PyYAML
